backtesting_framework/__init__.py
backtesting_framework/Core/__init__.py
backtesting_framework/Core/app.py
backtesting_framework/Core/Backtester.py
backtesting_framework/Core/Calendar.py
backtesting_framework/Core/Result.py
backtesting_framework/Core/Strategy.py
backtesting_framework/Strategies/__init__.py
backtesting_framework/Strategies/BollingerBands.py
backtesting_framework/Strategies/BuyAndHold.py
backtesting_framework/Strategies/KeltnerChannelStrategy.py
backtesting_framework/Strategies/MeanReversion.py
backtesting_framework/Strategies/MinVariance.py
backtesting_framework/Strategies/MovingAverage.py
backtesting_framework/Strategies/PairsTrading.py
backtesting_framework/Strategies/Quality.py
backtesting_framework/Strategies/RSI.py
backtesting_framework/Strategies/Size.py
backtesting_framework/Strategies/Value.py
backtesting_framework/Strategies/Volatility_Trend.py
backtesting_framework/Utils/__init__.py
backtesting_framework/Utils/Tools.py
backtesting_framework-0.1.6.dist-info/METADATA
backtesting_framework-0.1.6.dist-info/WHEEL
backtesting_framework-0.1.6.dist-info/RECORD
